LICENSE
MANIFEST.in
README.md
setup.py
bayeosgatewayclient/__init__.py
bayeosgatewayclient/bayeosframe.py
bayeosgatewayclient/bayeosgatewayclient.py
bayeosgatewayclient.egg-info/PKG-INFO
bayeosgatewayclient.egg-info/SOURCES.txt
bayeosgatewayclient.egg-info/dependency_links.txt
bayeosgatewayclient.egg-info/top_level.txt