Metadata-Version: 1.1
Name: bayeosgatewayclient
Version: 0.2.6
Summary: A Python package to transfer client data to a BayEOS Gateway.
Home-page: UNKNOWN
Author: Anja Kleebaum, Stefan Holzheu, Oliver Archner
Author-email: Anja.Kleebaum@stmail.uni-bayreuth.de
License: GPL2
Keywords: bayeos gateway client
Platform: UNKNOWN
Classifier: Programming Language :: Python
